Metadata-Version: 2.1
Name: discord-webhookspy
Version: 1.1.1
Summary: A simple Python library for Discord webhooks
Author: AlperenS
Author-email: ajaxseson1@gmail.com
Classifier: Programming Language :: Python :: 3
Classifier: License :: OSI Approved :: MIT License
Classifier: Operating System :: OS Independent
